netbox_secretstore/__init__.py
netbox_secretstore/admin.py
netbox_secretstore/constants.py
netbox_secretstore/exceptions.py
netbox_secretstore/filtersets.py
netbox_secretstore/hashers.py
netbox_secretstore/navigation.py
netbox_secretstore/querysets.py
netbox_secretstore/tables.py
netbox_secretstore/template_content.py
netbox_secretstore/urls.py
netbox_secretstore/views.py
netbox_secretstore/api/__init__.py
netbox_secretstore/api/nested_serializers.py
netbox_secretstore/api/serializers.py
netbox_secretstore/api/urls.py
netbox_secretstore/api/views.py
netbox_secretstore/forms/__init__.py
netbox_secretstore/forms/fields.py
netbox_secretstore/forms/secrets.py
netbox_secretstore/graphql/__init__.py
netbox_secretstore/graphql/schema.py
netbox_secretstore/graphql/types.py
netbox_secretstore/migrations/0001_initial.py
netbox_secretstore/migrations/0002_rename_table.py
netbox_secretstore/migrations/0003_modify_objectchange_records.py
netbox_secretstore/migrations/0004_secretrole_tags.py
netbox_secretstore/migrations/0005_alter_secret_created_alter_secret_id_and_more.py
netbox_secretstore/migrations/__init__.py
netbox_secretstore/models/__init__.py
netbox_secretstore/models/secrets.py
netbox_secretstore/static/netbox_secretstore/secrets.js
netbox_secretstore/static/netbox_secretstore/secrets.js.map
netbox_secretstore/templates/netbox_secretstore/activate_keys.html
netbox_secretstore/templates/netbox_secretstore/secret.html
netbox_secretstore/templates/netbox_secretstore/secret_delete.html
netbox_secretstore/templates/netbox_secretstore/secret_edit.html
netbox_secretstore/templates/netbox_secretstore/secret_import.html
netbox_secretstore/templates/netbox_secretstore/secretrole.html
netbox_secretstore/templates/netbox_secretstore/sessionkey_delete.html
netbox_secretstore/templates/netbox_secretstore/userkey.html
netbox_secretstore/templates/netbox_secretstore/userkey_edit.html
netbox_secretstore/templates/netbox_secretstore/buttons/add.html
netbox_secretstore-1.4.1.dist-info/LICENSE.txt
netbox_secretstore-1.4.1.dist-info/METADATA
netbox_secretstore-1.4.1.dist-info/WHEEL
netbox_secretstore-1.4.1.dist-info/top_level.txt
netbox_secretstore-1.4.1.dist-info/RECORD
